distconfig/__init__.py
distconfig/api.py
distconfig/config.py
distconfig/utils.py
distconfig/backends/__init__.py
distconfig/backends/base.py
distconfig/backends/consul.py
distconfig/backends/etcd.py
distconfig/backends/execution_context.py
distconfig/backends/zookeeper.py
distconfig/tests/__init__.py
distconfig/tests/integration/__init__.py
distconfig/tests/integration/base.py
distconfig/tests/integration/test_consul_backend.py
distconfig/tests/integration/test_etcd_backend.py
distconfig/tests/integration/test_zookeeper_backend.py
distconfig/tests/unit/__init__.py
distconfig/tests/unit/test_backend.py
distconfig/tests/unit/test_config.py
distconfig3-1.0.1.dist-info/LICENSE
distconfig3-1.0.1.dist-info/METADATA
distconfig3-1.0.1.dist-info/WHEEL
distconfig3-1.0.1.dist-info/top_level.txt
distconfig3-1.0.1.dist-info/RECORD
