Metadata-Version: 2.1
Name: distconfig3
Version: 1.0.1
Summary: Library to manage configuration using Zookeeper, Etcd, Consul
Home-page: http://github.com/alexferl/distconfig/
Maintainer: Alexandre Ferland
Maintainer-email: aferlandqc@gmail.com
License: Apache License, Version 2.0
Keywords: Configuration management zookeeper etcd consul
Platform: UNKNOWN
Classifier: Programming Language :: Python
Classifier: License :: OSI Approved :: Apache Software License
Classifier: Operating System :: OS Independent
Classifier: Programming Language :: Python :: 3
Classifier: Programming Language :: Python :: 3.7
Classifier: Programming Language :: Python :: 3.8
Classifier: Programming Language :: Python :: 3.9
Classifier: Topic :: Internet
Classifier: Topic :: Software Development :: Libraries :: Python Modules
Classifier: Intended Audience :: Developers
Provides-Extra: consul
Requires-Dist: python-consul (>=0.3.15) ; extra == 'consul'
Provides-Extra: etcd
Requires-Dist: python-etcd (>=0.3.3) ; extra == 'etcd'
Provides-Extra: gevent
Requires-Dist: gevent (>=1.4.0) ; extra == 'gevent'
Provides-Extra: zookeeper
Requires-Dist: kazoo (>=2.0) ; extra == 'zookeeper'
